exampleproject_crida/__init__.py
exampleproject_crida/example_usage.py
exampleproject_crida-0.2.3.dist-info/METADATA
exampleproject_crida-0.2.3.dist-info/WHEEL
exampleproject_crida-0.2.3.dist-info/RECORD
