Metadata-Version: 2.1
Name: exampleproject-crida
Version: 0.2.3
Summary: 
Author: Sergi Mas-Pujol
Author-email: smas@e-crida.enaire.es
Requires-Python: >=3.10,<4.0
Classifier: Programming Language :: Python :: 3
Classifier: Programming Language :: Python :: 3.10
Classifier: Programming Language :: Python :: 3.11
